schedulesy_qrcode/__init__.py
schedulesy_qrcode/ceph.py
schedulesy_qrcode/config.py
schedulesy_qrcode/generate.py
schedulesy_qrcode/main.py
schedulesy_qrcode/parse.py
schedulesy_qrcode/refresh.py
schedulesy_qrcode/render.py
schedulesy_qrcode-1.0.6.dist-info/METADATA
schedulesy_qrcode-1.0.6.dist-info/WHEEL
schedulesy_qrcode-1.0.6.dist-info/entry_points.txt
schedulesy_qrcode-1.0.6.dist-info/RECORD
