Metadata-Version: 2.1
Name: schedulesy-qrcode
Version: 1.0.6
Summary: Schedulesy - Generates QRCodes for public schedules of classrooms
Author: DIP - Université de Strasbourg
Author-email: dnum-dip@unistra.fr
Requires-Python: >=3.10,<4.0
Classifier: Programming Language :: Python :: 3
Classifier: Programming Language :: Python :: 3.10
Classifier: Programming Language :: Python :: 3.11
Classifier: Programming Language :: Python :: 3.12
Classifier: Programming Language :: Python :: 3.13
Requires-Dist: Jinja2 (>=3.1.2,<4.0.0)
Requires-Dist: boto3 (>=1.28.43,<2.0.0)
Requires-Dist: pillow (<11)
Requires-Dist: qrcode[pil] (>=7.3.1,<8.0.0)
Requires-Dist: requests (>=2.28.1,<3.0.0)
